jupyterlab_linewrapcellouput/__init__.py
jupyterlab_linewrapcellouput/_version.py
jupyterlab_linewrapcellouput/labextension/build_log.json
jupyterlab_linewrapcellouput/labextension/package.json
jupyterlab_linewrapcellouput/labextension/static/c96d3b4564cb09356f70b9d6cd250a68cd4850ab2ddcff33951ff6d26fd7e5c7.png
jupyterlab_linewrapcellouput/labextension/static/lib_index_js.be1e036af2685cb69c33.js
jupyterlab_linewrapcellouput/labextension/static/lib_index_js.be1e036af2685cb69c33.js.map
jupyterlab_linewrapcellouput/labextension/static/remoteEntry.9661af4b9d5a9b8177ba.js
jupyterlab_linewrapcellouput/labextension/static/remoteEntry.9661af4b9d5a9b8177ba.js.map
jupyterlab_linewrapcellouput/labextension/static/style.js
jupyterlab_linewrapcellouput/labextension/static/style_index_js.3890cbb301d609685760.js
jupyterlab_linewrapcellouput/labextension/static/style_index_js.3890cbb301d609685760.js.map
jupyterlab_linewrapcellouput/labextension/static/vendors-node_modules_css-loader_dist_runtime_api_js-node_modules_css-loader_dist_runtime_cssW-7d5e6f.99076841a25571159b5d.js
jupyterlab_linewrapcellouput/labextension/static/vendors-node_modules_css-loader_dist_runtime_api_js-node_modules_css-loader_dist_runtime_cssW-7d5e6f.99076841a25571159b5d.js.map
jupyterlab_linewrapcellouput-0.1.1.data/data/share/jupyter/labextensions/jupyterlab_linewrapcellouput/build_log.json
jupyterlab_linewrapcellouput-0.1.1.data/data/share/jupyter/labextensions/jupyterlab_linewrapcellouput/install.json
jupyterlab_linewrapcellouput-0.1.1.data/data/share/jupyter/labextensions/jupyterlab_linewrapcellouput/package.json
jupyterlab_linewrapcellouput-0.1.1.data/data/share/jupyter/labextensions/jupyterlab_linewrapcellouput/static/c96d3b4564cb09356f70b9d6cd250a68cd4850ab2ddcff33951ff6d26fd7e5c7.png
jupyterlab_linewrapcellouput-0.1.1.data/data/share/jupyter/labextensions/jupyterlab_linewrapcellouput/static/lib_index_js.be1e036af2685cb69c33.js
jupyterlab_linewrapcellouput-0.1.1.dist-info/LICENSE
jupyterlab_linewrapcellouput-0.1.1.dist-info/METADATA
jupyterlab_linewrapcellouput-0.1.1.dist-info/WHEEL
jupyterlab_linewrapcellouput-0.1.1.dist-info/top_level.txt
jupyterlab_linewrapcellouput-0.1.1.dist-info/RECORD
